bazis/contrib/authing/__init__.py
bazis/contrib/authing/_version.py
bazis/contrib/authing/apps.py
bazis/contrib/authing/conf.py
bazis/contrib/authing/router.py
bazis/contrib/authing/routes.py
bazis/contrib/authing/schemas.py
bazis/contrib/authing/service.py
bazis/contrib/authing/locale/en/LC_MESSAGES/django.mo
bazis/contrib/authing/locale/en/LC_MESSAGES/django.po
bazis/contrib/authing/locale/ru/LC_MESSAGES/django.mo
bazis/contrib/authing/locale/ru/LC_MESSAGES/django.po
bazis/contrib/authing/services/__init__.py
bazis/contrib/authing/services/google/__init__.py
bazis/contrib/authing/services/google/conf.py
bazis/contrib/authing/services/google/router.py
bazis/contrib/authing/services/google/routes.py
bazis/contrib/authing/services/password/__init__.py
bazis/contrib/authing/services/password/router.py
bazis/contrib/authing/services/password/routes.py
bazis/contrib/authing/services/password/schemas.py
bazis_authing-2.2.0.dist-info/METADATA
bazis_authing-2.2.0.dist-info/WHEEL
bazis_authing-2.2.0.dist-info/top_level.txt
bazis_authing-2.2.0.dist-info/RECORD
