Metadata-Version: 2.4
Name: bazis-authing
Version: 2.2.0
Summary: Authentication and authorization module for Bazis framework.
Author-email: Ilya Kharyn <ilya.tt07@gmail.com>
Maintainer-email: Ilya Kharyn <ilya.tt07@gmail.com>
Project-URL: Home, https://github.com/ecofuture-tech/bazis-authing
Keywords: bazis,django,fastapi,pydantic,framework,jsonapi,authentication,authorization,oauth
Classifier: Intended Audience :: Developers
Classifier: Topic :: Software Development :: Libraries :: Python Modules
Classifier: Operating System :: OS Independent
Classifier: Programming Language :: Python :: 3
Classifier: Programming Language :: Python :: 3.12
Classifier: Programming Language :: Python :: 3.13
Classifier: Programming Language :: Python :: 3.14
Classifier: Framework :: Django
Classifier: Framework :: FastAPI
Requires-Python: >=3.12
Requires-Dist: bazis
Requires-Dist: bazis-users
Requires-Dist: google-auth
Requires-Dist: google-auth-oauthlib
Requires-Dist: google-api-python-client
Requires-Dist: authlib
Requires-Dist: httpx
Provides-Extra: test
Requires-Dist: bazis-test-utils; extra == "test"
Provides-Extra: dev
Requires-Dist: ruff; extra == "dev"
